[
  {
    "pattern": "calendar",
    "type": "main",
    "counts": {
      "2011": 26345,
      "2012": 55214,
      "2013": 75216,
      "2014": 79214,
      "2015": 147549,
      "2016": 118198,
      "2017": 187466,
      "2018": 221583,
      "2019": 321980,
      "2020": 405897,
      "2021": 411998,
      "2022": 254204
    }
  },
  {
    "pattern": "calender",
    "type": "alt",
    "counts": {
      "2011": 2687,
      "2012": 6417,
      "2013": 7391,
      "2014": 7284,
      "2015": 8457,
      "2016": 4533,
      "2017": 7332,
      "2018": 8825,
      "2019": 11228,
      "2020": 14132,
      "2021": 18420,
      "2022": 8818
    }
  }
]